sequencer/.metainfo
sequencer/__init__.py
sequencer/commons.py
sequencer/guesser.py
sequencer/tracer.py
sequencer/chain/__init__.py
sequencer/chain/cli.py
sequencer/dgm/__init__.py
sequencer/dgm/cli.py
sequencer/dgm/db.py
sequencer/dgm/errors.py
sequencer/dgm/model.py
sequencer/ise/__init__.py
sequencer/ise/api.py
sequencer/ise/cli.py
sequencer/ise/errors.py
sequencer/ise/ise.xsd
sequencer/ise/model.py
sequencer/ise/parser.py
sequencer/ise/rc.py
sequencer/ism/__init__.py
sequencer/ism/algo.py
sequencer/ism/cli.py
sequencer-1.8.4.data/data/conf/config
sequencer-1.8.4.data/data/doc/man/man1/chain.1
sequencer-1.8.4.data/data/doc/man/man1/depmake.1
sequencer-1.8.4.data/data/doc/man/man1/dgmdb.1
sequencer-1.8.4.data/data/doc/man/man1/graphrules.1
sequencer-1.8.4.data/data/doc/man/man1/knowntypes.1
sequencer-1.8.4.data/data/doc/man/man1/seqexec.1
sequencer-1.8.4.data/data/doc/man/man1/seqmake.1
sequencer-1.8.4.data/data/doc/man/man1/sequencer.1
sequencer-1.8.4.data/data/doc/man/man1/sequencer.chain.1
sequencer-1.8.4.data/data/doc/man/man1/sequencer.depmake.1
sequencer-1.8.4.data/data/doc/man/man1/sequencer.dgmdb.1
sequencer-1.8.4.data/data/doc/man/man1/sequencer.graphrules.1
sequencer-1.8.4.data/data/doc/man/man1/sequencer.knowntypes.1
sequencer-1.8.4.data/data/doc/man/man1/sequencer.seqexec.1
sequencer-1.8.4.data/data/doc/man/man1/sequencer.seqmake.1
sequencer-1.8.4.data/data/doc/man/man5/seqexec.5
sequencer-1.8.4.data/data/doc/man/man5/seqmake.5
sequencer-1.8.4.data/data/doc/man/man5/sequencer.seqexec.5
sequencer-1.8.4.data/data/doc/man/man5/sequencer.seqmake.5
sequencer-1.8.4.data/data/doc/misc/ChangeLog
sequencer-1.8.4.data/data/doc/misc/example.makerules.sh
sequencer-1.8.4.data/data/doc/misc/example.seqexec.xml
sequencer-1.8.4.data/data/doc/misc/example.seqmake.xml
sequencer-1.8.4.data/data/doc/misc/hello_world.seqexec.xml
sequencer-1.8.4.data/data/doc/misc/remote.seqexec.xml
sequencer-1.8.4.data/scripts/guesser
sequencer-1.8.4.dist-info/DESCRIPTION.rst
sequencer-1.8.4.dist-info/METADATA
sequencer-1.8.4.dist-info/RECORD
sequencer-1.8.4.dist-info/WHEEL
sequencer-1.8.4.dist-info/metadata.json
sequencer-1.8.4.dist-info/top_level.txt
