Metadata-Version: 2.0
Name: sequencer
Version: 1.8.4
Summary: The sequencer is used to execute actions in a specified order (for example power on/off clusters)
Home-page: http://vigneras.github.com/sequencer
Author: Pierre Vignéras
Author-email: pierre.vigneras@gmail.com
License: GPL v3
Download-URL: http://github.com/downloads/vigneras/sequencer/sequencer-1.8.4.tar.gz
Keywords: sequencer,executor,engine
Platform: GNU/Linux
Platform: BSD
Platform: MacOSX
Classifier: Development Status :: 5 - Production/Stable
Classifier: Environment :: Console
Classifier: Intended Audience :: System Administrators
Classifier: License :: OSI Approved :: GNU General Public License (GPL)
Classifier: Operating System :: MacOS :: MacOS X
Classifier: Operating System :: POSIX :: BSD
Classifier: Operating System :: POSIX :: Linux
Classifier: Programming Language :: Python
Classifier: Topic :: Software Development :: Libraries :: Python Modules
Classifier: Topic :: System :: Clustering
Classifier: Topic :: System :: Distributed Computing
Provides: sequencer
Requires-Dist: ClusterShell (>=1.5)
Requires-Dist: lxml (>=2.2.3)
Requires-Dist: pydot
Requires-Dist: python-graph-core (>=1.7.0)
Requires-Dist: python-graph-dot (>=1.7.0)
